xiblint/__init__.py
xiblint/__main__.py
xiblint/config.py
xiblint/patch_element_tree.py
xiblint/xibcontext.py
xiblint/xibutils.py
xiblint/xmlutils.py
xiblint/rules/__init__.py
xiblint/rules/accessibility_format.py
xiblint/rules/accessibility_labels_for_image_buttons.py
xiblint/rules/accessibility_labels_for_images.py
xiblint/rules/accessibility_labels_for_text_with_placeholder.py
xiblint/rules/autolayout_frames.py
xiblint/rules/automation_identifiers.py
xiblint/rules/automation_identifiers_for_outlet_labels.py
xiblint/rules/color_assets.py
xiblint/rules/enforce_runtime_attributes.py
xiblint/rules/enforce_system_properties.py
xiblint/rules/named_colors.py
xiblint/rules/no_attributed_string_colors.py
xiblint/rules/no_simulated_metrics.py
xiblint/rules/no_trait_variations.py
xiblint/rules/no_view_controller_links_to_other_bundles.py
xiblint/rules/simulated_metrics_retina4_0.py
xiblint/rules/strict_font_names.py
xiblint/rules/strict_font_sizes.py
xiblint/rules/strict_fonts.py
xiblint/rules/unavailable_custom_classes.py
xiblint/rules/unavailable_system_classes.py
xiblint-0.10.4.dist-info/LICENSE
xiblint-0.10.4.dist-info/METADATA
xiblint-0.10.4.dist-info/NOTICE
xiblint-0.10.4.dist-info/WHEEL
xiblint-0.10.4.dist-info/entry_points.txt
xiblint-0.10.4.dist-info/top_level.txt
xiblint-0.10.4.dist-info/RECORD
